document_ocr-0.2.dist-info/METADATA
document_ocr-0.2.dist-info/RECORD
document_ocr-0.2.dist-info/WHEEL
document_ocr-0.2.dist-info/top_level.txt
ocr/__init__.py
ocr/pan.py
panocr/__init__.py
panocr/parse.py
